LICENSE
Makefile
README.md
setup.cfg
setup.py
.github/workflows/release.yml
.github/workflows/tests.yml
assembler/__init__.py
assembler/arguments.py
assembler/code.py
assembler/main.py
assembler/parser.py
assembler/symbols.py
assembler/utils.py
hack_assembler.egg-info/PKG-INFO
hack_assembler.egg-info/SOURCES.txt
hack_assembler.egg-info/dependency_links.txt
hack_assembler.egg-info/entry_points.txt
hack_assembler.egg-info/not-zip-safe
hack_assembler.egg-info/pbr.json
hack_assembler.egg-info/top_level.txt
tests/test_code.py
tests/test_parser.py
tests/test_symbols.py