Metadata-Version: 1.1
Name: hack-assembler
Version: 1.2.0
Summary: nand2tetris hack assembler
Home-page: https://github.com/ITD27M01/hack-assembler
Author: itd27m01
Author-email: igortiunov@gmail.com
License: Apache License 2.0
Platform: UNKNOWN
Classifier: Programming Language :: Python :: 3
Classifier: Programming Language :: Python :: 3.8
Classifier: License :: OSI Approved :: Apache Software License
Classifier: Operating System :: OS Independent
